fashiondata00/__init__.py
fashiondata00-0.1.4.dist-info/METADATA
fashiondata00-0.1.4.dist-info/WHEEL
fashiondata00-0.1.4.dist-info/top_level.txt
fashiondata00-0.1.4.dist-info/RECORD
