Metadata-Version: 2.1
Name: fashiondata00
Version: 0.1.4
Summary: Excel-style conditional aggregation with AND/OR logic for pandas
Author: KWON KI YONG
Author-email: fashiondata00@inu.ac.kr
Requires-Python: >=3.13
Requires-Dist: pandas
